django_export-1.11.0.dist-info/DESCRIPTION.rst
django_export-1.11.0.dist-info/METADATA
django_export-1.11.0.dist-info/RECORD
django_export-1.11.0.dist-info/WHEEL
django_export-1.11.0.dist-info/metadata.json
django_export-1.11.0.dist-info/top_level.txt
export/__init__.py
export/fields.py
export/forms.py
export/models.py
export/tasks.py
export/tools.py
export/utils.py
export/serializers/__init__.py
export/serializers/csv_serializer.py
export/templates/export/export_form.html
export/tests/__init__.py
export/tests/test_export_tool.py
export/tests/test_supported_fields.py
