Metadata-Version: 2.0
Name: django-export
Version: 1.11.0
Summary: Django app allowing for filtered exporting of model data.
Home-page: http://github.com/praekelt/django-export
Author: Praekelt Consulting
Author-email: dev@praekelt.com
License: UNKNOWN
Platform: UNKNOWN
Classifier: Programming Language :: Python
Classifier: License :: OSI Approved :: BSD License
Classifier: Development Status :: 4 - Beta
Classifier: Operating System :: OS Independent
Classifier: Framework :: Django
Classifier: Intended Audience :: Developers
Classifier: Topic :: Internet :: WWW/HTTP :: Dynamic Content
Requires-Dist: django-object-tools
Requires-Dist: pyyaml (>=3.11)
